{"nodes":[{"pos":[32,96],"content":"Data entities - Sales and marketing (Execution) | Microsoft Docs","needQuote":true,"needEscape":true,"nodes":[{"content":"Data entities - Sales and marketing (Execution) | Microsoft Docs","pos":[0,64]}]},{"pos":[110,256],"content":"This article provides a list of the data entities that are available for the Sales and marketing execution functionality in Microsoft Dynamics AX.","needQuote":true,"needEscape":true,"nodes":[{"content":"This article provides a list of the data entities that are available for the Sales and marketing execution functionality in Microsoft Dynamics AX.","pos":[0,146]}]},{"pos":[671,718],"content":"Data entities - Sales and marketing (Execution)","linkify":"Data entities - Sales and marketing (Execution)","nodes":[{"content":"Data entities - Sales and marketing (Execution)","pos":[0,47]}]},{"content":"This article provides a list of the data entities that are available for the Sales and marketing execution functionality in Microsoft Dynamics AX.","pos":[720,866]},{"pos":[868,891],"content":"Available data entities","linkify":"Available data entities","nodes":[{"content":"Available data entities","pos":[0,23]}]},{"content":"Suggested sequence","pos":[917,935]},{"content":"Entity name","pos":[937,948]},{"content":"Area","pos":[950,954]},{"content":"Entity type","pos":[956,967]},{"content":"Dependency","pos":[969,979]},{"content":"Comments","pos":[981,989]},{"pos":[991,1027],"content":"<bpt id=\"p1\">**</bpt>28.1.011 SLM – Commissions Setup<ept id=\"p1\">**</ept>","source":"**28.1.011 SLM – Commissions Setup**"},{"content":"1","pos":[1029,1030]},{"content":"Commission sales group","pos":[1032,1054]},{"content":"Sales and marketing","pos":[1056,1075]},{"content":"Setup","pos":[1077,1082]},{"content":"None","pos":[1084,1088]},{"pos":[1090,1127],"content":"<bpt id=\"p1\">**</bpt>28.1.012 SLM - Summary Parameters<ept id=\"p1\">**</ept>","source":"**28.1.012 SLM - Summary Parameters**"},{"content":"2","pos":[1129,1130]},{"content":"Sales summary update parameters","pos":[1132,1163]},{"content":"Sales and marketing","pos":[1165,1184]},{"content":"Setup","pos":[1186,1191]},{"content":"None","pos":[1193,1197]},{"pos":[1199,1235],"content":"<bpt id=\"p1\">**</bpt>28.1.013 SLM - Sales Order Setup<ept id=\"p1\">**</ept>","source":"**28.1.013 SLM - Sales Order Setup**"},{"content":"3","pos":[1237,1238]},{"content":"Sales order pools","pos":[1240,1257]},{"content":"Sales and marketing","pos":[1259,1278]},{"content":"Setup","pos":[1280,1285]},{"content":"None","pos":[1287,1291]},{"content":"4","pos":[1293,1294]},{"content":"Sales order origin codes","pos":[1296,1320]},{"content":"Sales and marketing","pos":[1322,1341]},{"content":"Setup","pos":[1343,1348]},{"content":"None","pos":[1350,1354]},{"content":"5","pos":[1356,1357]},{"content":"Sales order hold codes","pos":[1359,1381]},{"content":"Sales and marketing","pos":[1383,1402]},{"content":"Setup","pos":[1404,1409]},{"content":"None","pos":[1411,1415]},{"pos":[1417,1454],"content":"<bpt id=\"p1\">**</bpt>28.1.014 SLM - Distribution Setup<ept id=\"p1\">**</ept>","source":"**28.1.014 SLM - Distribution Setup**"},{"content":"6","pos":[1456,1457]},{"content":"Terms of delivery","pos":[1459,1476]},{"content":"Sales and marketing","pos":[1478,1497]},{"content":"Setup","pos":[1499,1504]},{"content":"None","pos":[1506,1510]},{"content":"7","pos":[1512,1513]},{"content":"Delivery modes","pos":[1515,1529]},{"content":"Sales and marketing","pos":[1531,1550]},{"content":"Setup","pos":[1552,1557]},{"content":"None","pos":[1559,1563]},{"content":"8","pos":[1565,1566]},{"content":"Reason of delivery","pos":[1568,1586]},{"content":"Sales and marketing","pos":[1588,1607]},{"content":"Setup","pos":[1609,1614]},{"content":"None","pos":[1616,1620]},{"content":"9","pos":[1622,1623]},{"content":"Destination code","pos":[1625,1641]},{"content":"Sales and marketing","pos":[1643,1662]},{"content":"Setup","pos":[1664,1669]},{"content":"None","pos":[1671,1675]},{"content":"10","pos":[1677,1679]},{"content":"Carrier","pos":[1681,1688]},{"content":"Sales and marketing","pos":[1690,1709]},{"content":"Setup","pos":[1711,1716]},{"content":"None","pos":[1718,1722]},{"pos":[1724,1753],"content":"<bpt id=\"p1\">**</bpt>28.1.015 SLM - Form Setup<ept id=\"p1\">**</ept>","source":"**28.1.015 SLM - Form Setup**"},{"content":"11","pos":[1755,1757]},{"content":"Packing slip form printing configurations","pos":[1759,1800]},{"content":"Sales and marketing","pos":[1802,1821]},{"content":"Setup","pos":[1823,1828]},{"content":"Document type must exist in the system.","pos":[1830,1869]},{"content":"12","pos":[1871,1873]},{"content":"Sales agreement form printing configurations","pos":[1875,1919]},{"content":"Sales and marketing","pos":[1921,1940]},{"content":"Setup","pos":[1942,1947]},{"content":"Document type must exist in the system.","pos":[1949,1988]},{"content":"13","pos":[1990,1992]},{"content":"Sales invoice form printing configurations","pos":[1994,2036]},{"content":"Sales and marketing","pos":[2038,2057]},{"content":"Setup","pos":[2059,2064]},{"content":"Document type must exist in the system.","pos":[2066,2105]},{"content":"14","pos":[2107,2109]},{"content":"Sales order confirmation form printing configurations","pos":[2111,2164]},{"content":"Sales and marketing","pos":[2166,2185]},{"content":"Setup","pos":[2187,2192]},{"content":"Document type must exist in the system.","pos":[2194,2233]},{"content":"15","pos":[2235,2237]},{"content":"Sales quotation form printing configurations","pos":[2239,2283]},{"content":"Sales and marketing","pos":[2285,2304]},{"content":"Setup","pos":[2306,2311]},{"content":"Document type must exist in the system.","pos":[2313,2352]},{"content":"16","pos":[2354,2356]},{"content":"Picking list form printing configurations","pos":[2358,2399]},{"content":"Sales and marketing","pos":[2401,2420]},{"content":"Setup","pos":[2422,2427]},{"content":"Document type must exist in the system.","pos":[2429,2468]},{"content":"17","pos":[2470,2472]},{"content":"Shipment form printing configurations","pos":[2474,2511]},{"content":"Sales and marketing","pos":[2513,2532]},{"content":"Setup","pos":[2534,2539]},{"content":"Document type must exist in the system.","pos":[2541,2580]},{"pos":[2582,2623],"content":"<bpt id=\"p1\">**</bpt>28.1.016 SLM - Prices Discounts Setup<ept id=\"p1\">**</ept>","source":"**28.1.016 SLM - Prices Discounts Setup**"},{"content":"18","pos":[2625,2627]},{"content":"Trade agreement journal name","pos":[2629,2657]},{"content":"Sales and marketing","pos":[2659,2678]},{"content":"Setup","pos":[2680,2685]},{"content":"None","pos":[2687,2691]},{"content":"19","pos":[2693,2695]},{"content":"Trade agreement journal table","pos":[2697,2726]},{"content":"Sales and marketing","pos":[2728,2747]},{"content":"Setup","pos":[2749,2754]},{"content":"None","pos":[2756,2760]},{"content":"20","pos":[2762,2764]},{"content":"Activate sales prices and discounts","pos":[2766,2801]},{"content":"Sales and marketing","pos":[2803,2822]},{"content":"Setup","pos":[2824,2829]},{"content":"None","pos":[2831,2835]},{"content":"21","pos":[2837,2839]},{"content":"Sales price smart rounding versions","pos":[2841,2876]},{"content":"Sales and marketing","pos":[2878,2897]},{"content":"Setup","pos":[2899,2904]},{"content":"None","pos":[2906,2910]},{"content":"22","pos":[2912,2914]},{"content":"Sales price smart rounding version rules","pos":[2916,2956]},{"content":"Sales and marketing","pos":[2958,2977]},{"content":"Setup","pos":[2979,2984]},{"content":"None","pos":[2986,2990]},{"content":"23","pos":[2992,2994]},{"content":"Sales price smart rounding version currencies","pos":[2996,3041]},{"content":"Sales and marketing","pos":[3043,3062]},{"content":"Setup","pos":[3064,3069]},{"content":"None","pos":[3071,3075]},{"pos":[3077,3115],"content":"<bpt id=\"p1\">**</bpt>28.1.017 SLM - External Item Setup<ept id=\"p1\">**</ept>","source":"**28.1.017 SLM - External Item Setup**"},{"content":"24","pos":[3117,3119]},{"content":"External item description customer groups","pos":[3121,3162]},{"content":"Sales and marketing","pos":[3164,3183]},{"content":"Setup","pos":[3185,3190]},{"content":"None","pos":[3192,3196]},{"content":"25","pos":[3198,3200]},{"content":"External item descriptions for customers","pos":[3202,3242]},{"content":"Sales and marketing","pos":[3244,3263]},{"content":"Setup","pos":[3265,3270]},{"content":"None","pos":[3272,3276]},{"pos":[3278,3311],"content":"<bpt id=\"p1\">**</bpt>28.1.018 SLM - Customer Setup<ept id=\"p1\">**</ept>","source":"**28.1.018 SLM - Customer Setup**"},{"content":"26","pos":[3313,3315]},{"content":"Customer classification groups","pos":[3317,3347]},{"content":"Sales and marketing","pos":[3349,3368]},{"content":"Setup","pos":[3370,3375]},{"content":"None","pos":[3377,3381]},{"pos":[3383,3417],"content":"<bpt id=\"p1\">**</bpt>28.1.019 SLM - Supp Item Setup<ept id=\"p1\">**</ept>","source":"**28.1.019 SLM - Supp Item Setup**"},{"content":"27","pos":[3419,3421]},{"content":"Supplementary item - customer groups","pos":[3423,3459]},{"content":"Sales and marketing","pos":[3461,3480]},{"content":"Setup","pos":[3482,3487]},{"content":"None","pos":[3489,3493]},{"pos":[3495,3527],"content":"<bpt id=\"p1\">**</bpt>28.1.020 SLM - Returns Setup<ept id=\"p1\">**</ept>","source":"**28.1.020 SLM - Returns Setup**"},{"content":"28","pos":[3529,3531]},{"content":"Return reason code groups","pos":[3533,3558]},{"content":"Sales and marketing","pos":[3560,3579]},{"content":"Setup","pos":[3581,3586]},{"content":"None","pos":[3588,3592]},{"content":"29","pos":[3594,3596]},{"content":"Return reason codes","pos":[3598,3617]},{"content":"Sales and marketing","pos":[3619,3638]},{"content":"Setup","pos":[3640,3645]},{"content":"None","pos":[3647,3651]},{"content":"30","pos":[3653,3655]},{"content":"Disposition code","pos":[3657,3673]},{"content":"Sales and marketing","pos":[3675,3694]},{"content":"Setup","pos":[3696,3701]},{"content":"None","pos":[3703,3707]},{"pos":[3709,3749],"content":"<bpt id=\"p1\">**</bpt>28.1.021 SLM - Discount Groups Setup<ept id=\"p1\">**</ept>","source":"**28.1.021 SLM - Discount Groups Setup**"},{"content":"31","pos":[3751,3753]},{"content":"Line discount customer groups","pos":[3755,3784]},{"content":"Sales and marketing","pos":[3786,3805]},{"content":"Setup","pos":[3807,3812]},{"content":"None","pos":[3814,3818]},{"content":"32","pos":[3820,3822]},{"content":"Multiline discount customer groups","pos":[3824,3858]},{"content":"Sales and marketing","pos":[3860,3879]},{"content":"Setup","pos":[3881,3886]},{"content":"None","pos":[3888,3892]},{"content":"33","pos":[3894,3896]},{"content":"Multiline discount item groups","pos":[3898,3928]},{"content":"Sales and marketing","pos":[3930,3949]},{"content":"Setup","pos":[3951,3956]},{"content":"None","pos":[3958,3962]},{"pos":[3964,3997],"content":"<bpt id=\"p1\">**</bpt>28.1.022 SLM - Policies Setup<ept id=\"p1\">**</ept>","source":"**28.1.022 SLM - Policies Setup**"},{"content":"34","pos":[3999,4001]},{"content":"Sales type document entry policies","pos":[4003,4037]},{"content":"Sales and marketing","pos":[4039,4058]},{"content":"Setup","pos":[4060,4065]},{"content":"None","pos":[4067,4071]},{"content":"35","pos":[4073,4075]},{"content":"Sales type document processing policies","pos":[4077,4116]},{"content":"Sales and marketing","pos":[4118,4137]},{"content":"Setup","pos":[4139,4144]},{"content":"None","pos":[4146,4150]},{"content":"36","pos":[4152,4154]},{"content":"Sales type document default values","pos":[4156,4190]},{"content":"Sales and marketing","pos":[4192,4211]},{"content":"Setup","pos":[4213,4218]},{"content":"None","pos":[4220,4224]},{"content":"37","pos":[4226,4228]},{"content":"Sales order line update parameters","pos":[4230,4264]},{"content":"Sales and marketing","pos":[4266,4285]},{"content":"Setup","pos":[4287,4292]},{"content":"None","pos":[4294,4298]},{"pos":[4300,4333],"content":"<bpt id=\"p1\">**</bpt>28.1.023 SLM - SLM Parameters<ept id=\"p1\">**</ept>","source":"**28.1.023 SLM - SLM Parameters**"},{"content":"38","pos":[4335,4337]},{"content":"Campaign creation policies","pos":[4339,4365]},{"content":"Sales and marketing","pos":[4367,4386]},{"content":"Setup","pos":[4388,4393]},{"content":"None","pos":[4395,4399]},{"content":"39","pos":[4401,4403]},{"content":"Lead processing policies","pos":[4405,4429]},{"content":"Sales and marketing","pos":[4431,4450]},{"content":"Setup","pos":[4452,4457]},{"content":"None","pos":[4459,4463]},{"content":"40","pos":[4465,4467]},{"content":"Marketing mail policies","pos":[4469,4492]},{"content":"Sales and marketing","pos":[4494,4513]},{"content":"Setup","pos":[4515,4520]},{"content":"None","pos":[4522,4526]},{"content":"41","pos":[4528,4530]},{"content":"Opportunity maintenance policies","pos":[4532,4564]},{"content":"Sales and marketing","pos":[4566,4585]},{"content":"Setup","pos":[4587,4592]},{"content":"None","pos":[4594,4598]},{"content":"42","pos":[4600,4602]},{"content":"Prospect creation policies","pos":[4604,4630]},{"content":"Sales and marketing","pos":[4632,4651]},{"content":"Setup","pos":[4653,4658]},{"content":"None","pos":[4660,4664]},{"content":"43","pos":[4666,4668]},{"content":"Prospect statistics default values","pos":[4670,4704]},{"content":"Sales and marketing","pos":[4706,4725]},{"content":"Setup","pos":[4727,4732]},{"content":"None","pos":[4734,4738]},{"content":"44","pos":[4740,4742]},{"content":"Sales activity creation policies","pos":[4744,4776]},{"content":"Sales and marketing","pos":[4778,4797]},{"content":"Setup","pos":[4799,4804]},{"content":"None","pos":[4806,4810]},{"content":"45","pos":[4812,4814]},{"content":"Transaction logging policies","pos":[4816,4844]},{"content":"Sales and marketing","pos":[4846,4865]},{"content":"Setup","pos":[4867,4872]},{"content":"None","pos":[4874,4878]},{"pos":[4880,4929],"content":"<bpt id=\"p1\">**</bpt>28.1.024 SLM - Sales Agreement Classification<ept id=\"p1\">**</ept>","source":"**28.1.024 SLM - Sales Agreement Classification**"},{"content":"46","pos":[4931,4933]},{"content":"External sales agreement classification","pos":[4935,4974]},{"content":"Sales and marketing","pos":[4976,4995]},{"content":"Setup","pos":[4997,5002]},{"content":"None","pos":[5004,5008]},{"content":"47","pos":[5010,5012]},{"content":"Sales agreement classification","pos":[5014,5044]},{"content":"Sales and marketing","pos":[5046,5065]},{"content":"Setup","pos":[5067,5072]},{"content":"None","pos":[5074,5078]},{"content":"48","pos":[5080,5082]},{"content":"Sales agreement classification translation","pos":[5084,5126]},{"content":"Sales and marketing","pos":[5128,5147]},{"content":"Setup","pos":[5149,5154]},{"content":"Sales agreement classification","pos":[5156,5186]},{"pos":[5188,5220],"content":"<bpt id=\"p1\">**</bpt>28.4.006 SLM - Charges Setup<ept id=\"p1\">**</ept>","source":"**28.4.006 SLM - Charges Setup**"},{"content":"49","pos":[5222,5224]},{"content":"Customer charge groups","pos":[5226,5248]},{"content":"Sales and marketing","pos":[5250,5269]},{"content":"Master","pos":[5271,5277]},{"content":"None","pos":[5279,5283]},{"pos":[5285,5316],"content":"<bpt id=\"p1\">**</bpt>28.8.001 SLM - Sales Orders<ept id=\"p1\">**</ept>","source":"**28.8.001 SLM - Sales Orders**"},{"content":"50","pos":[5318,5320]},{"content":"Sales orders","pos":[5322,5334]},{"content":"Sales and marketing","pos":[5336,5355]},{"content":"Transactional","pos":[5357,5370]},{"content":"None","pos":[5372,5376]},{"content":"Demo data that is related to dates.","pos":[5378,5413]},{"content":"For example, <bpt id=\"p1\">**</bpt>Requested receipt date<ept id=\"p1\">**</ept> and <bpt id=\"p2\">**</bpt>Requested ship date<ept id=\"p2\">**</ept> must to be rolled forward to future dates when this data entity is imported by using demo data.","pos":[5414,5577],"source":" For example, **Requested receipt date** and **Requested ship date** must to be rolled forward to future dates when this data entity is imported by using demo data."},{"pos":[5579,5615],"content":"<bpt id=\"p1\">**</bpt>28.8.002 SLM - Sales Order Lines<ept id=\"p1\">**</ept>","source":"**28.8.002 SLM - Sales Order Lines**"},{"content":"51","pos":[5617,5619]},{"content":"Sales order lines","pos":[5621,5638]},{"content":"Sales and marketing","pos":[5640,5659]},{"content":"Transactional","pos":[5661,5674]},{"content":"Sales orders","pos":[5676,5688]},{"pos":[5690,5698],"content":"See also","linkify":"See also","nodes":[{"content":"See also","pos":[0,8]}]},{"pos":[5709,5866],"content":"<bpt id=\"p1\">[</bpt>Data entities and packages framework<ept id=\"p1\">](https://docs.microsoft.com/en-us/dynamics365/operations/dev-itpro/data-entities/using-data-entities-and-data-packages)</ept>","source":"[Data entities and packages framework](https://docs.microsoft.com/en-us/dynamics365/operations/dev-itpro/data-entities/using-data-entities-and-data-packages)"},{"pos":[5868,5998],"content":"<bpt id=\"p1\">[</bpt>Data entities home page<ept id=\"p1\">](https://docs.microsoft.com/en-us/dynamics365/operations/dev-itpro/data-entities/data-entities-home-page)</ept>","source":"[Data entities home page](https://docs.microsoft.com/en-us/dynamics365/operations/dev-itpro/data-entities/data-entities-home-page)"}],"content":"---\n# required metadata\n\ntitle: Data entities - Sales and marketing (Execution) | Microsoft Docs\ndescription: This article provides a list of the data entities that are available for the Sales and marketing execution functionality in Microsoft Dynamics AX.\nauthor: kfend\nmanager: AnnBe\nms.date: 2016-06-29 14:18:43\nms.topic: article\nms.prod: \nms.service: Dynamics365Operations\nms.technology: \n\n# optional metadata\n\n# keywords: \n# ROBOTS: \naudience: Developer\n# ms.devlang: \nms.reviewer: 51\nms.suite: Released- Dynamics AX 7.0.0\n# ms.tgt_pltfrm: \nms.custom: 95683\nms.assetid: 4575c4c5-0fe7-4c63-8895-b0ac79067045\nms.region: Global\n# ms.industry: \nms.author: kfend\n\n---\n\n# Data entities - Sales and marketing (Execution)\n\nThis article provides a list of the data entities that are available for the Sales and marketing execution functionality in Microsoft Dynamics AX.\n\nAvailable data entities\n-----------------------\n\nSuggested sequence\n\nEntity name\n\nArea\n\nEntity type\n\nDependency\n\nComments\n\n**28.1.011 SLM – Commissions Setup**\n\n1\n\nCommission sales group\n\nSales and marketing\n\nSetup\n\nNone\n\n**28.1.012 SLM - Summary Parameters**\n\n2\n\nSales summary update parameters\n\nSales and marketing\n\nSetup\n\nNone\n\n**28.1.013 SLM - Sales Order Setup**\n\n3\n\nSales order pools\n\nSales and marketing\n\nSetup\n\nNone\n\n4\n\nSales order origin codes\n\nSales and marketing\n\nSetup\n\nNone\n\n5\n\nSales order hold codes\n\nSales and marketing\n\nSetup\n\nNone\n\n**28.1.014 SLM - Distribution Setup**\n\n6\n\nTerms of delivery\n\nSales and marketing\n\nSetup\n\nNone\n\n7\n\nDelivery modes\n\nSales and marketing\n\nSetup\n\nNone\n\n8\n\nReason of delivery\n\nSales and marketing\n\nSetup\n\nNone\n\n9\n\nDestination code\n\nSales and marketing\n\nSetup\n\nNone\n\n10\n\nCarrier\n\nSales and marketing\n\nSetup\n\nNone\n\n**28.1.015 SLM - Form Setup**\n\n11\n\nPacking slip form printing configurations\n\nSales and marketing\n\nSetup\n\nDocument type must exist in the system.\n\n12\n\nSales agreement form printing configurations\n\nSales and marketing\n\nSetup\n\nDocument type must exist in the system.\n\n13\n\nSales invoice form printing configurations\n\nSales and marketing\n\nSetup\n\nDocument type must exist in the system.\n\n14\n\nSales order confirmation form printing configurations\n\nSales and marketing\n\nSetup\n\nDocument type must exist in the system.\n\n15\n\nSales quotation form printing configurations\n\nSales and marketing\n\nSetup\n\nDocument type must exist in the system.\n\n16\n\nPicking list form printing configurations\n\nSales and marketing\n\nSetup\n\nDocument type must exist in the system.\n\n17\n\nShipment form printing configurations\n\nSales and marketing\n\nSetup\n\nDocument type must exist in the system.\n\n**28.1.016 SLM - Prices Discounts Setup**\n\n18\n\nTrade agreement journal name\n\nSales and marketing\n\nSetup\n\nNone\n\n19\n\nTrade agreement journal table\n\nSales and marketing\n\nSetup\n\nNone\n\n20\n\nActivate sales prices and discounts\n\nSales and marketing\n\nSetup\n\nNone\n\n21\n\nSales price smart rounding versions\n\nSales and marketing\n\nSetup\n\nNone\n\n22\n\nSales price smart rounding version rules\n\nSales and marketing\n\nSetup\n\nNone\n\n23\n\nSales price smart rounding version currencies\n\nSales and marketing\n\nSetup\n\nNone\n\n**28.1.017 SLM - External Item Setup**\n\n24\n\nExternal item description customer groups\n\nSales and marketing\n\nSetup\n\nNone\n\n25\n\nExternal item descriptions for customers\n\nSales and marketing\n\nSetup\n\nNone\n\n**28.1.018 SLM - Customer Setup**\n\n26\n\nCustomer classification groups\n\nSales and marketing\n\nSetup\n\nNone\n\n**28.1.019 SLM - Supp Item Setup**\n\n27\n\nSupplementary item - customer groups\n\nSales and marketing\n\nSetup\n\nNone\n\n**28.1.020 SLM - Returns Setup**\n\n28\n\nReturn reason code groups\n\nSales and marketing\n\nSetup\n\nNone\n\n29\n\nReturn reason codes\n\nSales and marketing\n\nSetup\n\nNone\n\n30\n\nDisposition code\n\nSales and marketing\n\nSetup\n\nNone\n\n**28.1.021 SLM - Discount Groups Setup**\n\n31\n\nLine discount customer groups\n\nSales and marketing\n\nSetup\n\nNone\n\n32\n\nMultiline discount customer groups\n\nSales and marketing\n\nSetup\n\nNone\n\n33\n\nMultiline discount item groups\n\nSales and marketing\n\nSetup\n\nNone\n\n**28.1.022 SLM - Policies Setup**\n\n34\n\nSales type document entry policies\n\nSales and marketing\n\nSetup\n\nNone\n\n35\n\nSales type document processing policies\n\nSales and marketing\n\nSetup\n\nNone\n\n36\n\nSales type document default values\n\nSales and marketing\n\nSetup\n\nNone\n\n37\n\nSales order line update parameters\n\nSales and marketing\n\nSetup\n\nNone\n\n**28.1.023 SLM - SLM Parameters**\n\n38\n\nCampaign creation policies\n\nSales and marketing\n\nSetup\n\nNone\n\n39\n\nLead processing policies\n\nSales and marketing\n\nSetup\n\nNone\n\n40\n\nMarketing mail policies\n\nSales and marketing\n\nSetup\n\nNone\n\n41\n\nOpportunity maintenance policies\n\nSales and marketing\n\nSetup\n\nNone\n\n42\n\nProspect creation policies\n\nSales and marketing\n\nSetup\n\nNone\n\n43\n\nProspect statistics default values\n\nSales and marketing\n\nSetup\n\nNone\n\n44\n\nSales activity creation policies\n\nSales and marketing\n\nSetup\n\nNone\n\n45\n\nTransaction logging policies\n\nSales and marketing\n\nSetup\n\nNone\n\n**28.1.024 SLM - Sales Agreement Classification**\n\n46\n\nExternal sales agreement classification\n\nSales and marketing\n\nSetup\n\nNone\n\n47\n\nSales agreement classification\n\nSales and marketing\n\nSetup\n\nNone\n\n48\n\nSales agreement classification translation\n\nSales and marketing\n\nSetup\n\nSales agreement classification\n\n**28.4.006 SLM - Charges Setup**\n\n49\n\nCustomer charge groups\n\nSales and marketing\n\nMaster\n\nNone\n\n**28.8.001 SLM - Sales Orders**\n\n50\n\nSales orders\n\nSales and marketing\n\nTransactional\n\nNone\n\nDemo data that is related to dates. For example, **Requested receipt date** and **Requested ship date** must to be rolled forward to future dates when this data entity is imported by using demo data.\n\n**28.8.002 SLM - Sales Order Lines**\n\n51\n\nSales order lines\n\nSales and marketing\n\nTransactional\n\nSales orders\n\nSee also\n--------\n\n[Data entities and packages framework](https://docs.microsoft.com/en-us/dynamics365/operations/dev-itpro/data-entities/using-data-entities-and-data-packages)\n\n[Data entities home page](https://docs.microsoft.com/en-us/dynamics365/operations/dev-itpro/data-entities/data-entities-home-page)\n\n"}